table2ascii/__init__.py
table2ascii/alignment.py
table2ascii/annotations.py
table2ascii/exceptions.py
table2ascii/merge.py
table2ascii/options.py
table2ascii/preset_style.py
table2ascii/table_style.py
table2ascii/table_to_ascii.py
table2ascii-1.0.1.dist-info/LICENSE
table2ascii-1.0.1.dist-info/METADATA
table2ascii-1.0.1.dist-info/WHEEL
table2ascii-1.0.1.dist-info/top_level.txt
table2ascii-1.0.1.dist-info/RECORD
