Metadata-Version: 2.1
Name: table2ascii
Version: 1.0.1
Summary: Convert 2D Python lists into Unicode/Ascii tables
Home-page: https://github.com/DenverCoder1/table2ascii
Author: Jonah Lawrence
Author-email: jonah@freshidea.com
License: UNKNOWN
Platform: UNKNOWN
License-File: LICENSE
Requires-Dist: wcwidth (<1)
Requires-Dist: typing-extensions (>=3.7.4) ; python_version < "3.8"
Provides-Extra: dev
Requires-Dist: mypy (<1,>=0.982) ; extra == 'dev'
Requires-Dist: pre-commit (<3,>=2.0.0) ; extra == 'dev'
Requires-Dist: pyright (<2,>=1.0.0) ; extra == 'dev'
Requires-Dist: pytest (<8,>=6.0.0) ; extra == 'dev'
Requires-Dist: slotscheck (<1,>=0.1.0) ; extra == 'dev'
Requires-Dist: taskipy (<2,>=1.0.0) ; extra == 'dev'
Requires-Dist: tox (<5,>=3.0.0) ; extra == 'dev'
Provides-Extra: docs
Requires-Dist: enum-tools ; extra == 'docs'
Requires-Dist: sphinx ; extra == 'docs'
Requires-Dist: sphinx-autobuild ; extra == 'docs'
Requires-Dist: sphinx-toolbox ; extra == 'docs'
Requires-Dist: sphinxcontrib-trio ; extra == 'docs'
Requires-Dist: sphinxext-opengraph ; extra == 'docs'
Requires-Dist: sphinx-book-theme (==0.3.3) ; extra == 'docs'
